CHANGES.txt
MANIFEST.in
README.md
setup.cfg
setup.py
src/publickey/__init__.py
src/publickey/api.py
src/publickey/sshconfig.py
src/publickey/yamldata.py
src/publickey.egg-info/PKG-INFO
src/publickey.egg-info/SOURCES.txt
src/publickey.egg-info/dependency_links.txt
src/publickey.egg-info/entry_points.txt
src/publickey.egg-info/requires.txt
src/publickey.egg-info/top_level.txt