Metadata-Version: 1.1
Name: publickey
Version: 0.3
Summary: Control downloading/uploading publickeys.
Home-page: https://bitbucket.org/imagawa_yakata/publickey
Author: imagawa_yakata(oyakata)
Author-email: imagawa.hougikumaru@gmail.com
License: MIT
Platform: UNKNOWN
Classifier: Development Status :: 1 - Planning
Classifier: Intended Audience :: Developers
Classifier: Operating System :: POSIX :: Linux
Classifier: Programming Language :: Python
Classifier: Programming Language :: Python :: 2.7
Classifier: License :: OSI Approved :: MIT License
